ai_models_aurora/__init__.py
ai_models_aurora/_version.py
ai_models_aurora/model.py
ai_models_aurora-0.0.5.dist-info/LICENSE
ai_models_aurora-0.0.5.dist-info/METADATA
ai_models_aurora-0.0.5.dist-info/WHEEL
ai_models_aurora-0.0.5.dist-info/entry_points.txt
ai_models_aurora-0.0.5.dist-info/top_level.txt
ai_models_aurora-0.0.5.dist-info/RECORD
