Metadata-Version: 2.1
Name: ai-models-aurora
Version: 0.0.5
Summary: An ai-models plugin to run Microsoft's Aurora model
Author-email: "European Centre for Medium-Range Weather Forecasts (ECMWF)" <software.support@ecmwf.int>
License: Apache License
Project-URL: Repository, https://github.com/ecmwf-lab/ai-models-aurora
Keywords: ai,tools
Classifier: Development Status :: 4 - Beta
Classifier: Intended Audience :: Developers
Classifier: License :: OSI Approved :: Apache Software License
Classifier: Operating System :: OS Independent
Classifier: Programming Language :: Python :: 3 :: Only
Classifier: Programming Language :: Python :: 3.9
Classifier: Programming Language :: Python :: 3.10
Classifier: Programming Language :: Python :: 3.11
Classifier: Programming Language :: Python :: 3.12
Classifier: Programming Language :: Python :: Implementation :: CPython
Classifier: Programming Language :: Python :: Implementation :: PyPy
Requires-Python: >=3.10
License-File: LICENSE
Requires-Dist: microsoft-aurora >=1.1.0
Requires-Dist: ai-models >=0.6.4
Provides-Extra: dev
Requires-Dist: pre-commit ; extra == 'dev'
